{
  "name": "Advanced react",
  "description": "",
  "createdAt": "2025-12-17T04:43:24.946Z",
  "updatedAt": "2025-12-17T04:43:24.946Z",
  "prefixes": [
    {
      "id": "name",
      "name": "Name",
      "value": "John Doeeeeeeee",
      "type": "name"
    },
    {
      "id": "course",
      "name": "Course",
      "value": "Advanced React",
      "type": "course"
    },
    {
      "id": "org",
      "name": "Organization",
      "value": "Acme Corp",
      "type": "organization"
    },
    {
      "id": "date",
      "name": "Date",
      "value": "12/17/2025",
      "type": "date"
    }
  ],
  "elements": [
    {
      "id": "text-1765945477556",
      "type": "text",
      "content": "{{Name}}",
      "x": 775,
      "y": 48,
      "width": 300,
      "height": 40,
      "fontSize": 16,
      "color": "#ffffff",
      "fontFamily": "Arial"
    },
    {
      "id": "image-1765945598360",
      "type": "image",
      "src": null,
      "x": 200,
      "y": 200,
      "width": 150,
      "height": 150
    }
  ],
  "canvasDimensions": {
    "width": 1123,
    "height": 631.6875
  },
  "bgFileName": "batman_hd_batman_arkham_shadow-1280x720.jpg",
  "bgFileSize": 67771,
  "bgFileType": "image/jpeg",
  "version": "1.0"
}